inspectio/__init__.py
inspectio/inspectio.py
inspectio/patterns.yaml
inspectio-1.0.dist-info/LICENSE
inspectio-1.0.dist-info/METADATA
inspectio-1.0.dist-info/WHEEL
inspectio-1.0.dist-info/entry_points.txt
inspectio-1.0.dist-info/top_level.txt
inspectio-1.0.dist-info/RECORD
