Metadata-Version: 2.1
Name: inspectio
Version: 1.0
Summary: A secure log review tool that detects sensitive data using regex and spaCy
Home-page: https://github.com/unpluggedsec/inspectio.git
Author: Ayman Abdul Kareem
Classifier: Programming Language :: Python :: 3
Classifier: License :: Other/Proprietary License
Classifier: Operating System :: OS Independent
Requires-Python: >=3.7
License-File: LICENSE
Requires-Dist: spacy >=3.0.0
Requires-Dist: PyYAML >=5.4.1
Requires-Dist: argparse >=1.4.0
